shexstatements/__init__.py
shexstatements/application.py
shexstatements/cliargs.py
shexstatements/errors.py
shexstatements/parsetab.py
shexstatements/shexfromapplprofilecsv.py
shexstatements/shexfromcsv.py
shexstatements/shexfromdcapcsv.py
shexstatements/shexjfromcsv.py
shexstatements/shexstatement.py
shexstatements/shexstatementsparser.py
shexstatements/version.py
shexstatements/static/css/style.css
shexstatements/static/images/shexstatements.svg
shexstatements/templates/about.html
shexstatements/templates/api.html
shexstatements/templates/base.html
shexstatements/templates/docs.html
shexstatements/templates/quickstart.html
shexstatements/templates/shexstatements.html
shexstatements-0.7.data/scripts/shexstatements.sh
tests/__init__.py
tests/parsertest.py
tests/shexfromapcsvtest.py
tests/shexfromcsvtest.py
tests/shexgentest.py
tests/shexjfromcsvtest.py
tests/tests.py
tests/wdshexfromcsvtest.py
shexstatements-0.7.dist-info/LICENSE
shexstatements-0.7.dist-info/METADATA
shexstatements-0.7.dist-info/WHEEL
shexstatements-0.7.dist-info/top_level.txt
shexstatements-0.7.dist-info/RECORD
