Metadata-Version: 2.1
Name: shexstatements
Version: 0.7
Summary: Tool to generate shape expressions from CSV files
Home-page: https://github.com/johnsamuelwrites/ShExStatements
Author: John Samuel
Author-email: johnsamuelwrites@example.com
License: UNKNOWN
Platform: UNKNOWN
Classifier: Programming Language :: Python :: 3
Classifier: License :: OSI Approved :: GNU General Public License v3 or later (GPLv3+)
Classifier: Operating System :: OS Independent
Requires-Python: >=3.6
Requires-Dist: Flask (>=1.1.2)
Requires-Dist: PyShEx (>=0.7.14)
Requires-Dist: ply (>=3.11)
